{
  "generated": "2026-06-29",
  "range": [
    201,
    240
  ],
  "issue_counts": {
    "OK": 39,
    "sprawdzić terminologię": 1
  },
  "pages": [
    {
      "page": 201,
      "en_len": 3021,
      "pl_len": 2584,
      "ratio": 0.86,
      "en_refs": [
        "282",
        "283"
      ],
      "pl_refs": [
        "282",
        "283"
      ],
      "en_chapters": [],
      "pl_chapters": [],
      "issues": [
        "OK"
      ],
      "en_preview": "word on which thou hast questioned me: Who constraineth the man until he sinneth? Now, therefore, hearken: Of the constitution of man. \"Is the babe born, the power is feeble in it, and the soul is feeble in it, and also the counterfeiting spirit is feeble in it; in a word, the three together are feeble, without any one of them sensing anything, whether good or evil, because of the load of forgetfulness which is very ",
      "pl_preview": "słowa, o które mnie pytałaś: Kto przymusza człowieka, aż zgrzeszy? Teraz więc słuchaj: O budowie człowieka. Gdy dziecię się rodzi, moc jest w nim słaba, i dusza jest w nim słaba, i także duch naśladowczy jest w nim słaby; jednym słowem, te trzy razem są słabe, bez tego, by którekolwiek z nich odczuwało cokolwiek, czy dobre, czy złe, z powodu ciężaru zapomnienia, który jest bardzo ciężki. Nadto ciało także jest słabe."
    },
    {
      "page": 202,
      "en_len": 3033,
      "pl_len": 2414,
      "ratio": 0.8,
      "en_refs": [
        "284",
        "285",
        "286"
      ],
      "pl_refs": [
        "284",
        "285",
        "286"
      ],
      "en_chapters": [],
      "pl_chapters": [],
      "issues": [
        "OK"
      ],
      "en_preview": "The state of the sinful soul after death. \"Now, therefore, if |284. the time of that man is completed, first cometh forth the destiny and leadeth the man unto death through the rulers and their bonds with which they are bound through the Fate. p. 237 \"And thereafter the retributive receivers come and lead that soul out of the body. And thereafter the. retributive receivers spend three days circling round with that so",
      "pl_preview": "Stan duszy grzesznej po śmierci. Teraz więc, jeśli |284. czas owego człowieka zostaje dopełniony, najpierw wychodzi Los i prowadzi człowieka ku śmierci przez władców i ich więzy, którymi są związani przez Los. 'A potem przychodzą odbiorcy odpłaty i wyprowadzają tę duszę z ciała. A potem odbiorcy odpłaty przez trzy dni krążą z tą duszą po wszystkich krainach i wysyłają ją do wszystkich eonów świata. A duch naśladowczy"
    },
    {
      "page": 203,
      "en_len": 2596,
      "pl_len": 2166,
      "ratio": 0.83,
      "en_refs": [
        "287",
        "288"
      ],
      "pl_refs": [
        "287",
        "288"
      ],
      "en_chapters": [
        112
      ],
      "pl_chapters": [
        112
      ],
      "issues": [
        "OK"
      ],
      "en_preview": "CHAPTER 112 Of the ascension after death of the good soul that hath received the mysteries. Jesus continued again in the discourse and said: \"If on the contrary it is a soul which hath not hearkened unto the counterfeiting spirit in all its works, but hath become good and hath received the mysteries of the Light which are in the second space or even those which are in the third space which is within, when the time [o",
      "pl_preview": "|287. ROZDZIAŁ 112 O wzniesieniu po śmierci dobrej duszy, która otrzymała misteria. Jezus znowu ciągnął mowę i rzekł: 'Jeśli przeciwnie jest to dusza, która nie posłuchała ducha naśladowczego we wszystkich jego dziełach, lecz stała się dobra i otrzymała misteria Światłości, które są w drugiej przestrzeni albo nawet te, które są w trzeciej przestrzeni, która jest wewnątrz; gdy czas wyjścia tej duszy z ciała zostanie d"
    },
    {
      "page": 204,
      "en_len": 2950,
      "pl_len": 2410,
      "ratio": 0.82,
      "en_refs": [
        "289",
        "290"
      ],
      "pl_refs": [
        "289",
        "290"
      ],
      "en_chapters": [],
      "pl_chapters": [],
      "issues": [
        "OK"
      ],
      "en_preview": "\"And the destiny and the counterfeiting spirit follow that soul. Because the counterfeiting spirit is bound to it with the seals and the bonds of the rulers, it followeth thus that soul which travelleth on the ways with the counterfeiting spirit. \"It uttereth the mystery of the undoing of all the bonds and all the seals with which the rulers have bound the counterfeiting spirit to the soul. And when the soul uttereth",
      "pl_preview": "|289. A Los i duch naśladowczy idą za tą duszą. Ponieważ duch naśladowczy jest związany z nią pieczęciami i więzami władców, idzie więc za tą duszą, która podróżuje drogami z duchem naśladowczym. 'Wypowiada ona Misterium rozwiązania wszystkich więzów i wszystkich pieczęci, którymi władcy związali ducha naśladowczego z duszą. A gdy dusza wypowiada Misterium rozwiązania pieczęci, natychmiast więzy pieczęci, które są zw"
    },
    {
      "page": 205,
      "en_len": 2877,
      "pl_len": 2823,
      "ratio": 0.98,
      "en_refs": [
        "291",
        "292",
        "293"
      ],
      "pl_refs": [
        "291",
        "292",
        "293"
      ],
      "en_chapters": [
        113
      ],
      "pl_chapters": [
        113
      ],
      "issues": [
        "OK"
      ],
      "en_preview": "Of the ascension of that soul into the Inheritance. it |291. out of the æons of the Fate and lead it up into all the æons [above], it giving to every region its apology and the apology of all the regions and the seals to the tyrants of the king, the Adamas. And it giveth the apology of all the rulers of all the regions of the Left,--whose collective apologies and seals I will one day tell you when I shall tell you th",
      "pl_preview": "|291. ją z eonów Losu, i prowadzą ją w górę do wszystkich eonów powyżej, a ona daje każdej krainie jej obronę i obronę wszystkich krain, i pieczęcie tyranom króla Adamasa. I daje obronę wszystkich władców wszystkich krain Lewicy - których zbiorowe obrony i pieczęcie powiem wam pewnego dnia, gdy będę mówił wam o rozpostarciu wszechświata. 'A ponadto ci odbiorcy prowadzą tę duszę do Dziewicy Światłości, i ta dusza daje"
    },
    {
      "page": 206,
      "en_len": 3224,
      "pl_len": 2296,
      "ratio": 0.71,
      "en_refs": [
        "294",
        "295"
      ],
      "pl_refs": [
        "294",
        "295"
      ],
      "en_chapters": [],
      "pl_chapters": [],
      "issues": [
        "OK"
      ],
      "en_preview": "seals and the songs of praise to the region of the Light,'--concerning this word then thou hast spoken unto us aforetime, when they brought thee the piece ofThe piece of money which was brought unto Jesus. money and thou didst see that it was of silver and copper and didst ask: 'Whose is this image?' They said: 'The king's.' And when thou sawest that it was of silver and copper mixed, thou saidst: 'Give therefore the",
      "pl_preview": "To znaczy: jeśli dusza otrzymuje misteria, daje obronę wszystkim władcom i krainie |294. króla Adamasa; a dusza daje cześć i chwałę wszystkim z krainy Światłości. A słowo: \"Zalśniła, gdy ujrzałeś, że jest uczyniona ze srebra i miedzi\" - jest tego typem, że w niej jest moc Światłości, która jest subtelnym srebrem, i że w niej jest duch naśladowczy, który jest materialną miedzią. To, Panie mój, jest pierwsza myśl.' 'Dr"
    },
    {
      "page": 207,
      "en_len": 2711,
      "pl_len": 2465,
      "ratio": 0.91,
      "en_refs": [
        "296",
        "297"
      ],
      "pl_refs": [
        "296",
        "297"
      ],
      "en_chapters": [
        114
      ],
      "pl_chapters": [
        114
      ],
      "issues": [
        "OK"
      ],
      "en_preview": "it then hath not found it, the counterfeiting spirit leadeth the soul to the Virgin of Light, the judge; and the judge, the Virgin of Light, proveth the soul and findeth |296. that it hath sinned and, as she also hath not found the mysteries of the Light with it, she handeth it over to one of her receivers, and her receiver leadeth it and casteth it into the body, and it cometh not out of the changes of the body befo",
      "pl_preview": "jeśli więc go nie znalazła, duch naśladowczy prowadzi duszę do Dziewicy Światłości, sędziego; a sędzia, Dziewica Światłości, bada duszę i znajduje, |296. że zgrzeszyła, a ponieważ także nie znalazła przy niej misteriów Światłości, przekazuje ją jednemu ze swoich odbiorców, a jej odbiorca prowadzi ją i wrzuca w ciało, i nie wychodzi ona ze zmian ciała, zanim odda swój ostatni obieg.\" Co do tego słowa więc, Panie mój, "
    },
    {
      "page": 208,
      "en_len": 3012,
      "pl_len": 2566,
      "ratio": 0.85,
      "en_refs": [
        "298",
        "299",
        "300"
      ],
      "pl_refs": [
        "298",
        "299",
        "300"
      ],
      "en_chapters": [
        115
      ],
      "pl_chapters": [
        115
      ],
      "issues": [
        "OK"
      ],
      "en_preview": "are below man, know not. Now, therefore, Mary, question on what thou mayest question, and I will reveal it unto thee face to face without similitude.\" CHAPTER 115 And Mary answered and said: \"My Lord, in what type then do |298. the baptisms forgive sins? I heard thee say: 'The retributive servitors follow the soul, being witnesses to it for all the sins which it committeth, that they may convict it in the judgments.'",
      "pl_preview": "których także wszyscy bogowie, którzy są poniżej człowieka, nie znają. Teraz więc, Maryjo, pytaj o to, o co możesz pytać, a objawię ci to twarzą w twarz, bez podobieństwa”. ROZDZIAŁ 115 A Maryja odpowiedziała i rzekła: „Panie mój, w jakim typie więc |298. chrzty odpuszczają grzechy? Słyszałam, jak mówiłeś: 'Sługi odpłaty podążają za duszą, będąc jej świadkami we wszystkich grzechach, które popełnia, aby oskarżyć ją w"
    },
    {
      "page": 209,
      "en_len": 3023,
      "pl_len": 2592,
      "ratio": 0.86,
      "en_refs": [
        "301",
        "302"
      ],
      "pl_refs": [
        "301",
        "302"
      ],
      "en_chapters": [
        116
      ],
      "pl_chapters": [
        116
      ],
      "issues": [
        "OK"
      ],
      "en_preview": "How the baptisms purify sins. mysteries of the baptisms, then the mystery of them becometh a great, exceedingly violent, wise fire and it burneth up the sins and entereth into the soul secretly and consumeth all the sins which the counterfeiting spirit hath made fast on to it. And when it hath finished purifying all the sinsThe separation of the portions by the mystery of baptism. which the counterfeiting spirit hath",
      "pl_preview": "misteria chrztów - wtedy ich Misterium staje się wielkim, nadzwyczaj gwałtownym, mądrym ogniem; spala grzechy, wchodzi tajemnie do duszy i pochłania wszystkie grzechy, które duch naśladowczy umocował na niej. Jak chrzty oczyszczają grzechy. A gdy skończy oczyszczać wszystkie grzechy, które duch naśladowczy umocował na duszy, wchodzi tajemnie do ciała i ściga tajemnie wszystkich ścigających, i oddziela ich po stronie "
    },
    {
      "page": 210,
      "en_len": 2303,
      "pl_len": 1995,
      "ratio": 0.87,
      "en_refs": [
        "303",
        "304"
      ],
      "pl_refs": [
        "303",
        "304"
      ],
      "en_chapters": [
        117,
        118
      ],
      "pl_chapters": [
        117,
        118
      ],
      "issues": [
        "OK"
      ],
      "en_preview": "the bodies of the world, because it hath separated the counterfeiting spirit and the body and the destiny into one portion; the soul and the power on the other hand it hath separated into another portion;--that is: Three will be against two, and two against three.\" And when Mary had said this, the Saviour p. 251 said: \"Well said, thou spiritual and light-pure Mary. This is the solution of the word.\" CHAPTER 117 Mary ",
      "pl_preview": "ciałach świata, ponieważ oddzieliło ducha naśladowczego, ciało i Los w jedną część; duszę i moc zaś oddzieliło w inną część. To jest: trzech będzie przeciw dwóm, a dwóch przeciw trzem”. A gdy Maryja to powiedziała, Zbawca rzekł: „Dobrze powiedziałaś, ty duchowa i światło-czysta Maryjo. Oto jest rozwiązanie słowa”. ROZDZIAŁ 117 Maryja dalej pyta Jezusa. Maryja znowu odpowiedziała i rzekła: „Panie mój, nadal będę cię p"
    },
    {
      "page": 211,
      "en_len": 2697,
      "pl_len": 2524,
      "ratio": 0.94,
      "en_refs": [
        "305"
      ],
      "pl_refs": [
        "305"
      ],
      "en_chapters": [
        119
      ],
      "pl_chapters": [
        119
      ],
      "issues": [
        "OK"
      ],
      "en_preview": "aforetime concerning this word, saying: 'Blessed are they whose sins are forgiven and whose iniquities are covered.' \"And the word which thou hast spoken: 'The mystery of the First Mystery and the mystery of the Ineffable forgive all men who shall receive those mysteries, not only the sins which they have committed from the beginning onwards, but also they impute them not to them from this hour unto all eternity,'--c",
      "pl_preview": "dawniej o tym słowie, mówiąc: 'Błogosławieni ci, których grzechy są odpuszczone i których nieprawości są zakryte'. „A o słowie, które wypowiedziałeś: 'Misterium Pierwszego Misterium i Misterium Niewypowiadalnego odpuszczają wszystkim ludziom, którzy otrzymają owe misteria, nie tylko grzechy, które popełnili od początku, lecz także nie przypisują im ich od tej godziny aż po całą wieczność' - o tym słowie Dawid proroko"
    },
    {
      "page": 212,
      "en_len": 2494,
      "pl_len": 2303,
      "ratio": 0.92,
      "en_refs": [
        "307",
        "308"
      ],
      "pl_refs": [
        "307",
        "308"
      ],
      "en_chapters": [
        120
      ],
      "pl_chapters": [
        120
      ],
      "issues": [
        "OK"
      ],
      "en_preview": "because he hath received the gift of the First Mystery and hath not abided in it [sc. the gift]. Of the unending forgiveness of those who have received the mystery of the Ineffable. Mary answered and said: \"My Lord, all men who shall receive the mysteries of the mystery of the Ineffable, and have turned again, have transgressed and have ceased in their faith, and again thereafter, when they are still in life, p. 254 ",
      "pl_preview": "ponieważ otrzymał dar Pierwszego Misterium i nie wytrwał w nim. O nieustannym odpuszczeniu tym, którzy otrzymali Misterium Niewypowiadalnego. Maryja odpowiedziała i rzekła: „Panie mój, wszyscy ludzie, którzy otrzymają misteria Misterium Niewypowiadalnego, a potem znowu zawrócą, przekroczą prawo i ustaną w swojej wierze, a następnie znowu, gdy są jeszcze w życiu, zawrócą i będą pokutować - ile razy będzie im odpuszczo"
    },
    {
      "page": 213,
      "en_len": 2972,
      "pl_len": 2636,
      "ratio": 0.89,
      "en_refs": [
        "309",
        "310"
      ],
      "pl_refs": [
        "309",
        "310"
      ],
      "en_chapters": [],
      "pl_chapters": [],
      "issues": [
        "OK"
      ],
      "en_preview": "but if they turn, transgress, and cease in their faith, and if they go forth out of the body without having repented, they are no more fit from this hour onwards to return to the changes of the body, nor for anything at all, but they are cast out into the outer darkness, they will perish in that region and be non-existent for ever,'--concerning [this] word thou hast spoken unto us aforetime, saying: 'Salt is good; bu",
      "pl_preview": "lecz jeśli zawrócą, przekroczą prawo i ustaną w swojej wierze, a jeśli wyjdą z ciała bez pokuty, od tej godziny nie są już zdatne powrócić do zmian ciała ani do czegokolwiek w ogóle, lecz zostają wyrzucone w zewnętrzną ciemność; zginą w owej krainie i będą nieistniejące na wieki' - co do tego słowa mówiłeś nam przedtem, mówiąc: 'Sól jest dobra; lecz jeśli sól stanie się jałowa, czym ją posolą? Nie nadaje się ani na g"
    },
    {
      "page": 214,
      "en_len": 2539,
      "pl_len": 2350,
      "ratio": 0.93,
      "en_refs": [
        "311",
        "312"
      ],
      "pl_refs": [
        "311",
        "312"
      ],
      "en_chapters": [
        121,
        122
      ],
      "pl_chapters": [
        121,
        122
      ],
      "issues": [
        "OK"
      ],
      "en_preview": "CHAPTER 121 When then the Saviour had said this unto his disciples, he said unto them: \"Understand ye in what manner I speak with you?\" Mary interpreteth from a former saying. Mary answered and said: \"Yea, my Lord, with precision have I precisely followed all the words which thou hast said. Concerning this word then thou hast spoken unto us aforetime: 'If the house-holder knew at what hour in the night the thief come",
      "pl_preview": "ROZDZIAŁ 121 Gdy więc Zbawca powiedział to swoim uczniom, rzekł do nich: „Czy rozumiecie, w jaki sposób mówię z wami?” Maryja interpretuje z dawniejszego powiedzenia. Maryja odpowiedziała i rzekła: „Tak, Panie mój, z dokładnością podążyłam za wszystkimi słowami, które wypowiedziałeś. O tym słowie mówiłeś nam przedtem: 'Gdyby gospodarz wiedział, o której godzinie nocy przychodzi złodziej, aby włamać się do domu, czuwa"
    },
    {
      "page": 215,
      "en_len": 2404,
      "pl_len": 2159,
      "ratio": 0.9,
      "en_refs": [
        "313"
      ],
      "pl_refs": [
        "313"
      ],
      "en_chapters": [
        123
      ],
      "pl_chapters": [
        123
      ],
      "issues": [
        "OK"
      ],
      "en_preview": "commanded them. He said unto Peter: \"Lo, three times have I baptized this soul, and yet at this third time she hath not done what is worthy of the mysteries of the Light. Wherefor then cloth she make her body good for nothing? Now, therefore, Peter, perform the mystery which cutteth off the souls from the inheritances of the Light; perform that mystery in order that it may cut off the soul of this woman from the Inhe",
      "pl_preview": "nakazał. Rzekł do Piotra: „Oto trzy razy ochrzciłem tę duszę, a jednak za tym trzecim razem nie uczyniła tego, co godne misteriów Światłości. Dlaczego więc czyni swoje ciało bezpożytecznym? Teraz więc, Piotrze, dokonaj Misterium, które odcina dusze od Dziedzictw Światłości; dokonaj tego Misterium, aby odcięło duszę tej kobiety od Dziedzictwa Światłości”. Gdy więc Zbawca to powiedział, wystawił Piotra na próbę, aby zo"
    },
    {
      "page": 216,
      "en_len": 3002,
      "pl_len": 2730,
      "ratio": 0.91,
      "en_refs": [
        "314",
        "315",
        "316"
      ],
      "pl_refs": [
        "314",
        "315",
        "316"
      ],
      "en_chapters": [
        124
      ],
      "pl_chapters": [
        124
      ],
      "issues": [
        "OK"
      ],
      "en_preview": "he hath received, or |314. rather give him a mystery out of the lower mysteries,--is it lawful, or not?\" In the case of repentance only higher mysteries than those previously received can remit sins. The Saviour answered and said unto Mary: \"Amēn, amēn, I say unto you: Neither the mystery which he hath received, nor the lower hearken unto him, to forgive his sins; but it is the mysteries which are higher than those w",
      "pl_preview": "otrzymał, albo |314. raczej dać mu Misterium z niższych misteriów - czy wolno, czy nie? W przypadku pokuty tylko misteria wyższe niż wcześniej otrzymane mogą odpuścić grzechy. Zbawca odpowiedział i rzekł do Maryi: 'Amen, amen, mówię wam: ani Misterium, które otrzymał, ani niższe nie wysłuchują go, aby odpuścić jego grzechy; lecz misteria, które są wyższe niż te, które otrzymał, wysłuchują go i odpuszczają jego grzech"
    },
    {
      "page": 217,
      "en_len": 2760,
      "pl_len": 2469,
      "ratio": 0.89,
      "en_refs": [
        "317",
        "318"
      ],
      "pl_refs": [
        "317",
        "318"
      ],
      "en_chapters": [
        125
      ],
      "pl_chapters": [
        125
      ],
      "issues": [
        "OK"
      ],
      "en_preview": "Mary interpreteth the same from a former saying. When then the Saviour had said this, Mary started forward and said: \"My Lord, my light-man hath ears, and I have understood the whole word which thou hast spoken. Concerning this word then thou hast spoken unto us in a similitude: p. 262 [paragraph continues] 'The slave who knew the will of his lord and made not ready nor did the will of his lord, will receive great bl",
      "pl_preview": "Maryja interpretuje to samo z dawniejszego powiedzenia. Gdy więc Zbawca to powiedział, Maryja wystąpiła i rzekła: 'Panie mój, mój człowiek światłości ma uszy i zrozumiałam całe słowo, które wypowiedziałeś. Co do tego słowa więc mówiłeś nam w podobieństwie: 'Sługa, który znał wolę swego pana, a nie przygotował się ani nie uczynił woli swego pana, otrzyma wielkie razy; lecz ten, który nie znał i nie uczynił, będzie zas"
    },
    {
      "page": 218,
      "en_len": 2168,
      "pl_len": 1844,
      "ratio": 0.85,
      "en_refs": [
        "319"
      ],
      "pl_refs": [
        "319"
      ],
      "en_chapters": [],
      "pl_chapters": [],
      "issues": [
        "OK"
      ],
      "en_preview": "circuits of the changes of the body, and coming back into the world are some of those in this present time who have hearkened unto me, how I taught, who at the completion of the number of the perfect souls will find the mysteries of the Light and receive them and come to the gates of the Light and find that the number of the perfect souls is complete, which is the completion of the First Mystery and the gnosis of the",
      "pl_preview": "i wracając na świat, będą wśród nich niektórzy z obecnego czasu, którzy słuchali mnie, jak nauczałem, którzy przy dopełnieniu liczby dusz doskonałych znajdą misteria Światłości, otrzymają je i przyjdą do bram Światłości, i znajdą, że liczba dusz doskonałych jest dopełniona, co jest dopełnieniem Pierwszego Misterium i gnozą wszechświata. I znajdą, że zamknąłem bramy Światłości i że niemożliwe jest, aby ktokolwiek wsze"
    },
    {
      "page": 219,
      "en_len": 2208,
      "pl_len": 2192,
      "ratio": 0.99,
      "en_refs": [
        "320",
        "321"
      ],
      "pl_refs": [
        "320",
        "321"
      ],
      "en_chapters": [
        126
      ],
      "pl_chapters": [
        126
      ],
      "issues": [
        "OK"
      ],
      "en_preview": "CHAPTER 126 AND Mary continued again and said unto Jesus: \"In what type is the outer darkness; or rather how many regions of chastisement are there in it?\" Of the dragon of the outer darkness. And Jesus answered and said unto Mary: \"The outer darkness is a great dragon, whose tail is in his mouth, outside the whole world and surrounding the whole world. And there are many regions of chastisement within it. There are ",
      "pl_preview": "ROZDZIAŁ 126 A Maryja znowu kontynuowała i rzekła do Jezusa: 'W jakim typie jest zewnętrzna ciemność? Albo raczej: ile jest w niej krain karania?' O smoku zewnętrznej ciemności. A Jezus odpowiedział i rzekł do Maryi: 'Zewnętrzna ciemność jest wielkim smokiem, którego ogon jest w jego paszczy, poza całym światem i otaczającym cały świat. I jest w niej wiele krain karania. Jest dwanaście potężnych |320. lochów karania,"
    },
    {
      "page": 220,
      "en_len": 2695,
      "pl_len": 2360,
      "ratio": 0.88,
      "en_refs": [
        "322",
        "323"
      ],
      "pl_refs": [
        "322",
        "323"
      ],
      "en_chapters": [
        127
      ],
      "pl_chapters": [
        127
      ],
      "issues": [
        "OK"
      ],
      "en_preview": "\"And in the eleventh dungeon is a multitude of rulers,--and every one of them hath seven cat-faced heads in his authentic face. And the great one over them is called in his region Rōchar.' \"And in the twelfth dungeon is an exceedingly great multitude of rulers, and every one of them hath seven dog-faced heads in his authentic face. And the great one over them is called in his region 'Chrēmaōr.' \"These rulers then of ",
      "pl_preview": "'A w jedenastym lochu jest mnogość władców, i każdy z nich ma siedem głów o obliczu kota w swoim prawdziwym obliczu. A wielki nad nimi zwany jest w swojej krainie \"Rochar\". 'A w dwunastym lochu jest nadzwyczaj wielka mnogość władców, i każdy z nich ma siedem głów o obliczu psa w swoim prawdziwym obliczu. A wielki nad nimi zwany jest w swojej krainie \"Chremaor\". 'Ci więc władcy owych dwunastu lochów są wewnątrz smoka "
    },
    {
      "page": 221,
      "en_len": 2537,
      "pl_len": 2261,
      "ratio": 0.89,
      "en_refs": [
        "324",
        "325"
      ],
      "pl_refs": [
        "324",
        "325"
      ],
      "en_chapters": [
        128
      ],
      "pl_chapters": [
        128
      ],
      "issues": [
        "OK"
      ],
      "en_preview": "these twelve names are different one from another; but the twelve are one in the other, so that he who speaketh one name, speaketh all. These then will I tell you at the expansion of the universe. Thus then is fashioned the outer darkness,--that is the dragon.\" When then the Saviour had said this, Mary answered and said |324. unto the Saviour: \"My Lord, are then the chastisements of that dragon far more terrible comp",
      "pl_preview": "'I tych dwanaście imion różni się jedno od drugiego; lecz dwanaście jest jedno w drugim, tak że ten, kto wypowiada jedno imię, wypowiada wszystkie. Te więc powiem wam przy rozpostarciu wszechświata. Tak więc ukształtowana jest zewnętrzna ciemność - to jest smok.' Gdy więc Zbawca to powiedział, Maryja odpowiedziała i rzekła |324. do Zbawcy: 'Panie mój, czy więc karania owego smoka są o wiele straszniejsze w porównaniu"
    },
    {
      "page": 222,
      "en_len": 3083,
      "pl_len": 2147,
      "ratio": 0.7,
      "en_refs": [
        "326",
        "327"
      ],
      "pl_refs": [
        "326",
        "327"
      ],
      "en_chapters": [],
      "pl_chapters": [],
      "issues": [
        "OK"
      ],
      "en_preview": "Mary further questioneth Jesus. Mary answered and said: \"My Lord, if a good man hath accomplished all the mysteries and he hath a kinsman, in a word he hath a man, and that man is an impious [one] who hath committed all sins and is deserving of the outer darkness, and he hath not repented, or he hath completed his number of circuits in the changes of the body, and that man hath done nothing useful, p. 270 and he hath",
      "pl_preview": "Maryja dalej pyta Jezusa. Maryja odpowiedziała i rzekła: 'Panie mój, jeśli dobry człowiek dokonał wszystkich misteriów i ma krewnego - jednym słowem, ma człowieka - a ten człowiek jest bezbożny, popełnił wszystkie grzechy i zasługuje na zewnętrzną ciemność, i nie pokutował; albo dopełnił swojej liczby obiegów w zmianach ciała, a ten człowiek nie uczynił nic pożytecznego i wyszedł z ciała, i poznaliśmy z pewnością o n"
    },
    {
      "page": 223,
      "en_len": 2778,
      "pl_len": 2309,
      "ratio": 0.83,
      "en_refs": [
        "328",
        "329",
        "330"
      ],
      "pl_refs": [
        "328",
        "329",
        "330"
      ],
      "en_chapters": [
        129
      ],
      "pl_chapters": [
        129
      ],
      "issues": [
        "OK"
      ],
      "en_preview": "or it is in the judgments of the rulers; in a word, the receivers of Melchisedec |328. will snatch it away out of all the regions in which it is, and will lead it into the region of the Midst before the Virgin of Light, and the Virgin of Light proveth it and seeth the sign of the kingdom of the Ineffable which is on that soul. \"And if it hath not yet completed its number of circuits in the changes of the soul, or [in",
      "pl_preview": "|330.\\n\\n'A nadto, jeśli dopełniła obiegów zmian, niech dusza ta zostanie zaprowadzona przed siedem dziewic Światłości, które są nad chrztami, i niech zastosują je do duszy, i opieczętują ją znakiem królestwa Niewypowiadalnego, i poprowadzą ją do porządków Światłości.\" 'To więc będziecie mówić, gdy dokonujecie Misterium. 'Amen, mówię wam: dusza, za którą będziecie się modlić, jeśli zaprawdę jest w smoku zewnętrznej c"
    },
    {
      "page": 224,
      "en_len": 2953,
      "pl_len": 2445,
      "ratio": 0.83,
      "en_refs": [
        "332"
      ],
      "pl_refs": [
        "332"
      ],
      "en_chapters": [
        130
      ],
      "pl_chapters": [
        130
      ],
      "issues": [
        "OK"
      ],
      "en_preview": "CHAPTER 130 Mary pleadeth for those who have neglected the mysteries. And Mary continued and said unto the Saviour: \"My Lord, if a man hath received the mysteries of the Light which [are] in the first space from without, and when the time of the mysteries up to which they reach, is completed, and if that man continueth anew to receive mysteries of the mysteries which [are] within the mysteries which he hath already r",
      "pl_preview": "|332.\\n\\nO promieniach Światłości i strumieniach Światłości. Zbawca odpowiedział i rzekł do Maryi: 'Jeśli otrzymają Misterium, gdy są jeszcze w życiu, i jeśli wyjdą z ciała, stają się promieniami Światłości i strumieniami Światłości, i przenikają wszystkie krainy, aż dosięgną krainy swojego dziedzictwa. 'Lecz jeśli są grzesznikami i wyszli z ciała, a nie pokutowali, i jeśli dokonacie dla nich Misterium Niewypowiadaln"
    },
    {
      "page": 225,
      "en_len": 3326,
      "pl_len": 3889,
      "ratio": 1.17,
      "en_refs": [
        "333",
        "334"
      ],
      "pl_refs": [
        "333",
        "334"
      ],
      "en_chapters": [],
      "pl_chapters": [],
      "issues": [
        "OK"
      ],
      "en_preview": "Of the efficacy of the names of the twelve angels. \"And all men who shall find the mystery of one of the twelve names of that dragon of the outer darkness, and all men even if they are very great sinners, and they have first received the mysteries of the Light and thereafter have transgressed, or they have performed no mystery at all, then if they have completed their circuits in the changes, and if such men go forth",
      "pl_preview": "'Teraz więc, o Zbawco, zmiłuj się ze mną, aby nikt z naszych krewnych nie był w takim typie, i zmiłuj się nad wszystkimi duszami, które będą w tym typie; albowiem ty jesteś kluczem, który otwiera bramę wszechświata i zamyka bramę wszechświata, a twoje Misterium obejmuje ich wszystkich. Zmiłuj się więc, o Panie, nad takimi duszami. Albowiem wzywały imienia twoich misteriów choćby przez jeden jedyny dzień, i prawdziwie"
    },
    {
      "page": 226,
      "en_len": 2667,
      "pl_len": 1843,
      "ratio": 0.69,
      "en_refs": [
        "336"
      ],
      "pl_refs": [
        "336"
      ],
      "en_chapters": [
        131
      ],
      "pl_chapters": [
        131
      ],
      "issues": [
        "sprawdzić terminologię: aeon/æon -> eon"
      ],
      "en_preview": "p. 277 Mary interpreteth the same from a former saying. Mary then answered and said \"My Lord, this is the word which thou hast spoken unto us aforetime, in a similitude, saying: 'Make to yourselves a friend out of the Mamōn of unrighteousness, so that if ye remain behind, he may receive you into I the everlasting tents.' Who then is the Mamōn of unrighteousness, if not the dragon of the outer darkness? This is the wo",
      "pl_preview": "Maryja interpretuje to samo z dawniejszego powiedzenia. Wtedy Maryja odpowiedziała i rzekła: 'Panie mój, oto jest słowo, które wypowiedziałeś nam przedtem w podobieństwie, mówiąc: \"Uczyńcie sobie przyjaciela z Mamony nieprawości, aby jeśli pozostaniecie w tyle, przyjęła was do wiecznych namiotów.\" Kim więc jest Mamona nieprawości, jeśli nie smok zewnętrznej ciemności? Oto jest słowo: ten, kto zrozumie Misterium jedne"
    },
    {
      "page": 227,
      "en_len": 2852,
      "pl_len": 2779,
      "ratio": 0.97,
      "en_refs": [
        "337",
        "338",
        "339"
      ],
      "pl_refs": [
        "337",
        "338",
        "339"
      ],
      "en_chapters": [],
      "pl_chapters": [],
      "issues": [
        "OK"
      ],
      "en_preview": "wickedness, filled with all the different desires and all forgetfulness. And straightway, when that soul shall drink out of the cup, it forgetteth all the regions to which it hath gone, |337. and all the chastisements in which it hath travelled. AndOf the counterfeiting spirit. that cup of the water of forgetfulness becometh body outside the soul, and it resembleth the soul in all [its] figures and maketh [itself] li",
      "pl_preview": "|337. |338. |339.\\n\\nO kielichu zapomnienia. Zbawca odpowiedział i rzekł do Maryi: 'Nie schodzą w ten sposób na świat. Lecz władcy Losu, gdy stara dusza ma zejść przez nich, wtedy władcy tego wielkiego Losu, którzy są w krainach głowy eonów - to jest kraina zwana krainą królestwa Adamasa i kraina, która jest przed obliczem Dziewicy Światłości - wtedy władcy krainy owej głowy dają starej duszy kielich zapomnienia z na"
    },
    {
      "page": 228,
      "en_len": 3219,
      "pl_len": 2740,
      "ratio": 0.85,
      "en_refs": [
        "340",
        "341"
      ],
      "pl_refs": [
        "340",
        "341"
      ],
      "en_chapters": [],
      "pl_chapters": [],
      "issues": [
        "OK"
      ],
      "en_preview": "\"And that power is like the species of the soul in every form and resembleth it. It cannot be outside the soul, but remaineth inside it, as I have commanded it from the beginning. When I willed to cast it into the first Commandment, I gave it commandment to remain outside [? inside] the souls for the economy of the First Mystery. Jesus promiseth to reveal all in detail. \"And so I will tell you at the expansion of the",
      "pl_preview": "|340. |341.\\n\\n'A owa moc jest podobna do rodzaju duszy w każdej formie i przypomina ją. Nie może być na zewnątrz duszy, lecz pozostaje wewnątrz niej, jak nakazałem jej od początku. Gdy chciałem wrzucić ją do Pierwszego Przykazania, dałem jej przykazanie, aby pozostawała wewnątrz dusz dla ekonomii Pierwszego Misterium. Jezus obiecuje objawić wszystko szczegółowo. 'I tak powiem wam przy rozpostarciu wszechświata wszys"
    },
    {
      "page": 229,
      "en_len": 2841,
      "pl_len": 2679,
      "ratio": 0.94,
      "en_refs": [
        "342",
        "343"
      ],
      "pl_refs": [
        "342",
        "343"
      ],
      "en_chapters": [
        132
      ],
      "pl_chapters": [
        132
      ],
      "issues": [
        "OK"
      ],
      "en_preview": "\"For this cause therefore, have I said unto you aforetime: 'He who doth not abandon father and mother and come and follow after me, is not worthy of me.' I have, therefore, said at that time: Ye are to abandon your parents the rulers, that I may make you sons of the First Mystery for ever.\" CHAPTER 132 Salome is in doubt. And when |342. the Saviour had said this, Salome started forward and said: \"My Lord, if our pare",
      "pl_preview": "|342. |343.\\n\\n'Z tej przyczyny więc powiedziałem wam przedtem: \"Kto nie opuści ojca i matki, i nie przyjdzie, i nie pójdzie za mną, nie jest mnie godzien.\" Powiedziałem więc wtedy: macie opuścić waszych rodziców, władców, abym uczynił was synami Pierwszego Misterium na wieki.' ROZDZIAŁ 132 Salome ma wątpliwość. A gdy Zbawca to powiedział, Salome wystąpiła gwałtownie i rzekła: 'Panie mój, jeśli naszymi rodzicami są w"
    },
    {
      "page": 230,
      "en_len": 3101,
      "pl_len": 2350,
      "ratio": 0.76,
      "en_refs": [
        "344",
        "345",
        "346"
      ],
      "pl_refs": [
        "344",
        "345",
        "346"
      ],
      "en_chapters": [],
      "pl_chapters": [],
      "issues": [
        "OK"
      ],
      "en_preview": "thou hast made it do, in order that it may be chastized in all the regions of the judgments, so that it may not be able to go |344. on high to the Light and return into changes of the body.' \"In a word, they give commandment to the p. 284 counterfeiting spirit, saying: 'Do not agitate it at all at any hour unless it doth not speak mysteries and undo all the seals and all the bonds with which we have bound thee to it.",
      "pl_preview": "|344. |345. |346.\\n\\n'Jednym słowem, dają przykazanie duchowi naśladowczemu, mówiąc: \"Nie poruszaj jej w ogóle w żadnej godzinie, chyba że nie wypowiada misteriów i nie rozwiązuje wszystkich pieczęci i wszystkich więzów, którymi związaliśmy cię z nią. Lecz jeśli wypowiada misteria i rozwiązuje wszystkie pieczęcie i wszystkie więzy, i wypowiada obronę krainy, i jeśli przychodzi, wtedy pozwól jej wyjść, albowiem należy"
    },
    {
      "page": 231,
      "en_len": 3026,
      "pl_len": 2504,
      "ratio": 0.83,
      "en_refs": [
        "347",
        "348"
      ],
      "pl_refs": [
        "347",
        "348"
      ],
      "en_chapters": [],
      "pl_chapters": [],
      "issues": [
        "OK"
      ],
      "en_preview": "\"All this I will tell unto you and the species of every soul and the type, how they enter into the bodies, whether of men or of birds or of cattle or of wild beasts or of reptiles or of all the other species in the world. I will tell you their type, in what type they enter into men; I will tell it you at the expansion of the universe. \"Now, therefore, when the servitors of the rulers cast the one portion into the wom",
      "pl_preview": "|347. |348.\\n\\n'Wszystko to powiem wam, i rodzaj każdej duszy, i typ, jak wchodzą w ciała, czy ludzi, czy ptaków, czy bydła, czy dzikich zwierząt, czy pełzających, czy wszystkich innych rodzajów w świecie. Powiem wam ich typ, w jakim typie wchodzą w ludzi; powiem wam to przy rozpostarciu wszechświata. 'Teraz więc, gdy słudzy władców wrzucają jedną część w kobietę, a drugą w mężczyznę w sposób, który wam powiedziałem,"
    },
    {
      "page": 232,
      "en_len": 2880,
      "pl_len": 2357,
      "ratio": 0.82,
      "en_refs": [
        "349",
        "350"
      ],
      "pl_refs": [
        "349",
        "350"
      ],
      "en_chapters": [
        133
      ],
      "pl_chapters": [
        133
      ],
      "issues": [
        "OK"
      ],
      "en_preview": "spirit to it [the soul], they seal on the back of the skull of the plasm; and the day on which the rulers have breathed the power into the body, they seal on the brain which is in the midst of the head of the plasm and also on the inside [? the heart] of the plasm; and the number of years which the soul will spend in the body, they seal on the forehead which is on the plasm. And so they seal all those seals on the pl",
      "pl_preview": "|349. |350.\\n\\n'A dzień, w którym władcy tchnęli moc w ciało, pieczętują na mózgu, który jest pośrodku głowy plazmy, a także we wnętrzu plazmy; a liczbę lat, które dusza spędzi w ciele, pieczętują na czole, które jest na plazmie. I tak pieczętują wszystkie owe pieczęcie na plazmie. Powiem wam imiona wszystkich tych pieczęci przy rozpostarciu wszechświata; a po rozpostarciu wszechświata powiem wam, dlaczego wszystko s"
    },
    {
      "page": 233,
      "en_len": 2981,
      "pl_len": 2844,
      "ratio": 0.95,
      "en_refs": [
        "351",
        "352"
      ],
      "pl_refs": [
        "351",
        "352"
      ],
      "en_chapters": [],
      "pl_chapters": [],
      "issues": [
        "OK"
      ],
      "en_preview": "Mary answered and said: \"To all men then who are in the world, will all which is appointed them through the Fate, whether good or bad or sin or death or life,--in a word, will all which is appointed them through the rulers of the Fate, have to come unto them?\" There is no escape from the destiny. The Saviour answered and said unto Mary: \"Amēn, I say unto you: All which is appointed unto every one through the Fate, wh",
      "pl_preview": "|351. |352.\\n\\nMaryja odpowiedziała i rzekła: 'Wszystkim ludziom więc, którzy są na świecie - czy wszystko, co zostało im wyznaczone przez Los, czy dobre, czy złe, czy grzech, czy śmierć, czy życie - jednym słowem: czy wszystko, co zostało im wyznaczone przez władców Losu, musi przyjść do nich?' Nie ma ucieczki od przeznaczenia. Zbawca odpowiedział i rzekł do Maryi: 'Amen, mówię wam: wszystko, co zostało wyznaczone k"
    },
    {
      "page": 234,
      "en_len": 3030,
      "pl_len": 2873,
      "ratio": 0.95,
      "en_refs": [
        "354"
      ],
      "pl_refs": [
        "354"
      ],
      "en_chapters": [
        134
      ],
      "pl_chapters": [
        134
      ],
      "issues": [
        "OK"
      ],
      "en_preview": "the sinners who shall have faith in me and hearken unto me, and make them into refined light and lead them into the Light.\" CHAPTER 134 When then Jesus had said this, Mary answered and said: \"My Lord, if men go to seek and they come upon the doctrines of error, I whence then are they to know whether they belong to thee or not?\" The Saviour answered and said unto Mary: \"I have said unto you aforetime: 'Be ye as skilfu",
      "pl_preview": "|354.\\n\\nROZDZIAŁ 134 Gdy więc Jezus to powiedział, Maryja odpowiedziała i rzekła: 'Panie mój, jeśli ludzie pójdą szukać i natrafią na nauki błędu, skąd mają poznać, czy należą one do ciebie, czy nie?' Zbawca odpowiedział i rzekł do Maryi: 'Powiedziałem wam przedtem: bądźcie jak zręczni zmieniacze pieniędzy. Bierzcie dobre, odrzucajcie złe. Kryterium prawowierności. 'Teraz więc mówcie wszystkim ludziom, którzy chcą s"
    },
    {
      "page": 235,
      "en_len": 2381,
      "pl_len": 1575,
      "ratio": 0.66,
      "en_refs": [
        "356"
      ],
      "pl_refs": [
        "356"
      ],
      "en_chapters": [
        135
      ],
      "pl_chapters": [
        135
      ],
      "issues": [
        "OK"
      ],
      "en_preview": "accomplishment of the mystery of the First Mystery. This will I tell unto you when I have explained to you the expansion of the universe. For this cause, therefore, I have rent myself asunder and have brought p. 293 the mysteries into the world, because all are under sin and all are in need of the gift of the mysteries.\" CHAPTER 135 Mary answered and said unto the Saviour: \"My Lord, before thou didst come to the regi",
      "pl_preview": "|356.\\n\\nROZDZIAŁ 135 Maryja odpowiedziała i rzekła do Zbawcy: 'Panie mój, zanim przyszedłeś do krainy władców i zanim zstąpiłeś na świat, czy żadna dusza nie weszła do Światłości?' Żadna dusza nie weszła do Światłości przed przyjściem Pierwszego Misterium. Zbawca odpowiedział i rzekł do Maryi: 'Amen, amen, mówię wam: zanim przyszedłem na świat, żadna dusza nie weszła do Światłości. A teraz więc, gdy przyszedłem, otw"
    },
    {
      "page": 236,
      "en_len": 2032,
      "pl_len": 2119,
      "ratio": 1.04,
      "en_refs": [
        "357",
        "358"
      ],
      "pl_refs": [
        "357",
        "358"
      ],
      "en_chapters": [
        136
      ],
      "pl_chapters": [
        136
      ],
      "issues": [
        "OK"
      ],
      "en_preview": "into bodies which will all be righteous,--those which will find the mysteries of the Light, enter in and inherit the Light-kingdom.\" Mary answered and said: \"Blessed are we before all men because of these splendours which thou hast revealed unto us.\" The Saviour answered and said unto Mary and all the disciples: \"I will still reveal unto you all the splendours of the Height, from the interiors of the interiors to the",
      "pl_preview": "|357. |358.\\n\\nO duszach sprawiedliwych od Adama do Jezusa. 'Pozostałych patriarchów i sprawiedliwych od czasu Adama aż do teraz, którzy są w eonach i wszystkich porządkach władców - gdy przyszedłem do krainy eonów, sprawiłem przez Dziewicę Światłości, że zawrócili do ciał, które wszystkie będą sprawiedliwe, które znajdą misteria Światłości, wejdą i odziedziczą królestwo Światłości.' Maryja odpowiedziała i rzekła: 'B"
    },
    {
      "page": 237,
      "en_len": 2587,
      "pl_len": 2145,
      "ratio": 0.83,
      "en_refs": [
        "359",
        "360"
      ],
      "pl_refs": [
        "359",
        "360"
      ],
      "en_chapters": [],
      "pl_chapters": [],
      "issues": [
        "OK"
      ],
      "en_preview": "The interpretation of iaō. And Jesus made invocation, turning himself towards the four corners of the world with his disciples, who were all clad in linen garments, and saying: \"iaōiaōiaō.\" This is its interpretation: iōta, because the universe hath gone p. 296 forth; alpha, because it will turn itself back again; ōmega, because the completion of all the completeness will take place. He continueth to make invocation.",
      "pl_preview": "|359. |360.\\n\\nInterpretacja iao. A Jezus uczynił wezwanie, zwracając się ku czterem krańcom świata ze swoimi uczniami, którzy wszyscy byli odziani w lniane szaty, i mówił: 'iaoiaoiao.' Oto jego interpretacja: iota, ponieważ wszechświat wyszedł; alfa, ponieważ zawróci znowu ku sobie; omega, ponieważ dokona się dopełnienie wszelkiego dopełnienia. Kontynuuje wezwanie. A gdy Jezus to powiedział, rzekł: 'iaphtha iaphtha "
    },
    {
      "page": 238,
      "en_len": 2748,
      "pl_len": 2805,
      "ratio": 1.02,
      "en_refs": [
        "361",
        "362"
      ],
      "pl_refs": [
        "361",
        "362"
      ],
      "en_chapters": [
        137
      ],
      "pl_chapters": [
        137
      ],
      "issues": [
        "OK"
      ],
      "en_preview": "congress, procreating rulers, archangels, angels, servitors and decans, that Yew, the father of my father, came forth from the Right and bound them to a Fate-sphere. \"For there are twelve æons; over six Sabaōth, the Adamas, ruleth, and his brother Yabraōth ruleth over the other six. At that time then Yabraōth with his rulers had faith in the mysteries of the Light and was active in the mysteries of the Light and aban",
      "pl_preview": "|361. |362.\\n\\nO pokutujących i niepokutujących władcach. Jezus rzekł: 'To są krainy drogi Pośrodka. Albowiem stało się, gdy władcy Adamasa wzniecili bunt i uporczywie praktykowali obcowanie, płodząc władców, archaniołów, aniołów, sługi i dekanów, że Yew, ojciec mojego Ojca, wyszedł z Prawicy i związał ich w sferze Losu. 'Albowiem jest dwanaście eonów; nad sześcioma panuje Sabaoth, Adamas, a jego brat Yabraoth panuje"
    },
    {
      "page": 239,
      "en_len": 2456,
      "pl_len": 1999,
      "ratio": 0.81,
      "en_refs": [
        "363"
      ],
      "pl_refs": [
        "363"
      ],
      "en_chapters": [
        138
      ],
      "pl_chapters": [
        138
      ],
      "issues": [
        "OK"
      ],
      "en_preview": "confirming [it], so that he may set free all the rulers over whom he cometh, from the evil of their wickedness. And he gave him two æons, which are in face of those of Hermēs, for his dwelling. The incorruptible names of the regents. \"I have told you for the first time the names of these five great rulers with which the men of the world are wont to call them. Hearken now then that I may tell you also their incorrupti",
      "pl_preview": "|363.\\n\\nNiezniszczalne imiona regentów. 'Powiedziałem wam po raz pierwszy imiona tych pięciu wielkich władców, którymi ludzie świata zwykli ich nazywać. Słuchajcie teraz więc, abym powiedział wam także ich niezniszczalne imiona, którymi są: Orimouth odpowiada Kronosowi; Mounichounaphor odpowiada Aresowi; Tarpetanouph odpowiada Hermesowi; Chosi odpowiada Afrodycie; Chonbal odpowiada Zeusowi. To są ich niezniszczalne "
    },
    {
      "page": 240,
      "en_len": 2345,
      "pl_len": 2171,
      "ratio": 0.93,
      "en_refs": [
        "364",
        "365"
      ],
      "pl_refs": [
        "364",
        "365"
      ],
      "en_chapters": [
        139
      ],
      "pl_chapters": [
        139
      ],
      "issues": [
        "OK"
      ],
      "en_preview": "\"And I will give you the baptism of those of the Right, our region, and its ciphers and its seals and the manner of invocation for reaching thither. \"And I will give you the great mystery of the Treasury of the Light and |364. the manner of invocation for reaching thither. \"I will give you all the mysteries and all the gnoses, in order that ye may be called 'children of the fulness, perfected in all the gnoses and al",
      "pl_preview": "|364. |365.\\n\\n'I dam wam chrzest tych z Prawicy, naszej krainy, i jego szyfry, i jego pieczęcie, i sposób wezwania, aby tam dosięgnąć. 'I dam wam wielkie Misterium Skarbca Światłości i sposób wezwania, aby tam dosięgnąć. 'Dam wam wszystkie misteria i wszystkie gnozy, abyście zostali nazwani dziećmi Pełni, wydoskonalonymi we wszystkich gnozach i wszystkich misteriach. Błogosławieni jesteście ponad wszystkich ludzi na"
    }
  ]
}